bioviewer/__init__.py
bioviewer/signal.py
bioviewer/signaldata.py
bioviewer/signaldisplay.py
bioviewer/state.py
bioviewer/viewer.py
bioviewer-0.2.5.dist-info/METADATA
bioviewer-0.2.5.dist-info/WHEEL
bioviewer-0.2.5.dist-info/top_level.txt
bioviewer-0.2.5.dist-info/RECORD
