Metadata-Version: 2.2
Name: bioviewer
Version: 0.2.5
Summary: This library is designed to build visualization tools for biosignals such as EEG or ECG.
Home-page: https://github.com/MoritzAlkofer/BIOViewer
Author: Moritz Alkofer
Author-email: moritz.alkofer@protonmail.com
Requires-Dist: numpy>=2.0.2
Requires-Dist: matplotlib>=3.9.4
Requires-Dist: ipympl==0.9.6
Dynamic: author
Dynamic: author-email
Dynamic: description
Dynamic: description-content-type
Dynamic: home-page
Dynamic: requires-dist
Dynamic: summary
